song_executor/__init__.py
song_executor/cli.py
song_executor/executor.py
song_executor-0.1.0.dist-info/LICENSE
song_executor-0.1.0.dist-info/METADATA
song_executor-0.1.0.dist-info/WHEEL
song_executor-0.1.0.dist-info/entry_points.txt
song_executor-0.1.0.dist-info/RECORD
